datavisor/__init__.py
datavisor/config/__init__.py
datavisor/config/config.py
datavisor/config/config_builder.py
datavisor/config/error_logger.py
datavisor/config/exceptions.py
datavisor/data_handler/__init__.py
datavisor/data_handler/base_handler.py
datavisor/data_handler/annotation_handler/__init__.py
datavisor/data_handler/annotation_handler/handler.py
datavisor/data_handler/image_handler/__init__.py
datavisor/data_handler/image_handler/handler.py
datavisor/file_format/__init__.py
datavisor/file_format/visor_entry.py
datavisor/file_format/visor_file.py
datavisor/file_format/visor_header.py
datavisor/io_ops/__init__.py
datavisor/io_ops/visor_reader.py
datavisor/io_ops/visor_writer.py
datavisor-0.3.0.dist-info/LICENSE
datavisor-0.3.0.dist-info/METADATA
datavisor-0.3.0.dist-info/WHEEL
datavisor-0.3.0.dist-info/top_level.txt
datavisor-0.3.0.dist-info/RECORD
