Metadata-Version: 2.1
Name: datavisor
Version: 0.3.0
Summary: DataVisor a tool for producing binary aggregated data packs for machine learning trainings
Author-email: UYousafzai <umaryousafzai9@gmail.com>
License: MIT License
Project-URL: Homepage, https://github.com/UYousafzai/datavisor
Project-URL: Repository, https://github.com/UYousafzai/datavisor
Classifier: Programming Language :: Python :: 3
Classifier: License :: OSI Approved :: MIT License
Classifier: Operating System :: OS Independent
Requires-Python: >=3.7
License-File: LICENSE
Requires-Dist: Pillow
Requires-Dist: tqdm
